malort/__init__.py
malort/core.py
malort/stats.py
malort/test_helpers.py
malort/type_mappers.py
malort-0.0.4.dist-info/DESCRIPTION.rst
malort-0.0.4.dist-info/METADATA
malort-0.0.4.dist-info/metadata.json
malort-0.0.4.dist-info/RECORD
malort-0.0.4.dist-info/top_level.txt
malort-0.0.4.dist-info/WHEEL
