Metadata-Version: 2.0
Name: malort
Version: 0.0.4
Summary: JSON to Postgres Column Types
Home-page: https://github.com/wrobstory/malort
Author: Rob Story
Author-email: wrobstory@gmail.com
License: MIT License
Keywords: JSON Postgres postgres json
Platform: UNKNOWN
Classifier: Development Status :: 4 - Beta
Classifier: Programming Language :: Python
Classifier: Programming Language :: Python :: 2
Classifier: Programming Language :: Python :: 3
Classifier: License :: OSI Approved :: MIT License
Requires-Dist: dask (>=0.7.0)
Requires-Dist: dill (>=0.2.4)
Requires-Dist: numpy (>=1.9.2)
Requires-Dist: pandas (>=0.16.2)
Requires-Dist: python-dateutil (>=2.4.2)
Requires-Dist: pytz (>=2015.4)
Requires-Dist: six (>=1.9.0)
Requires-Dist: toolz (>=0.7.2)
Requires-Dist: wheel (>=0.24.0)
